ssh_utilities/__init__.py
ssh_utilities/connection.py
ssh_utilities/constants.py
ssh_utilities/exceptions.py
ssh_utilities/typeshed.py
ssh_utilities/utils.py
ssh_utilities/version.py
ssh_utilities/abstract/__init__.py
ssh_utilities/abstract/_builtins.py
ssh_utilities/abstract/_connection.py
ssh_utilities/abstract/_os.py
ssh_utilities/abstract/_os_path.py
ssh_utilities/abstract/_pathlib.py
ssh_utilities/abstract/_shutil.py
ssh_utilities/abstract/_subprocess.py
ssh_utilities/local/__init__.py
ssh_utilities/local/_builtins.py
ssh_utilities/local/_os.py
ssh_utilities/local/_os_path.py
ssh_utilities/local/_pathlib.py
ssh_utilities/local/_shutil.py
ssh_utilities/local/_subprocess.py
ssh_utilities/local/local.py
ssh_utilities/multi_connection/__init__.py
ssh_utilities/multi_connection/_delegated.py
ssh_utilities/multi_connection/_dict_interface.py
ssh_utilities/multi_connection/_persistence.py
ssh_utilities/multi_connection/multi_connection.py
ssh_utilities/remote/__init__.py
ssh_utilities/remote/_builtins.py
ssh_utilities/remote/_connection_wrapper.py
ssh_utilities/remote/_os.py
ssh_utilities/remote/_os_path.py
ssh_utilities/remote/_pathlib.py
ssh_utilities/remote/_shutil.py
ssh_utilities/remote/_subprocess.py
ssh_utilities/remote/path.py
ssh_utilities/remote/remote.py
ssh_utilities-0.15.2.dist-info/LICENSE
ssh_utilities-0.15.2.dist-info/METADATA
ssh_utilities-0.15.2.dist-info/WHEEL
ssh_utilities-0.15.2.dist-info/top_level.txt
ssh_utilities-0.15.2.dist-info/RECORD
