Metadata-Version: 2.1
Name: ssh-utilities
Version: 0.15.2
Summary: paramiko convenience wrapper
Home-page: https://github.com/marian-code/ssh-utilities
Author: Marián Rynik
Author-email: marian.rynik@outlook.sk
License: LGPL-2.1
Classifier: Development Status :: 4 - Beta
Classifier: Environment :: Console
Classifier: Intended Audience :: Developers
Classifier: Intended Audience :: End Users/Desktop
Classifier: License :: OSI Approved :: GNU Lesser General Public License v2 or later (LGPLv2+)
Classifier: Natural Language :: English
Classifier: Operating System :: OS Independent
Classifier: Programming Language :: Python :: 3.6
Classifier: Programming Language :: Python :: 3.7
Classifier: Programming Language :: Python :: 3.8
Classifier: Programming Language :: Python :: 3.9
Classifier: Programming Language :: Python :: 3
Classifier: Programming Language :: Python :: Implementation :: CPython
Classifier: Topic :: Utilities
Classifier: Topic :: Internet
Classifier: Typing :: Typed
License-File: LICENSE
Requires-Dist: paramiko (>=2.7.1)
Requires-Dist: typing-extensions (>=3.7.4.2)
Requires-Dist: colorama (>=0.4.3)
Requires-Dist: tqdm (>=4.47.0)
Provides-Extra: test
Requires-Dist: unittest ; extra == 'test'
Requires-Dist: paramiko (>=2.7.1) ; extra == 'test'
Requires-Dist: typing-extensions (>=3.7.4.2) ; extra == 'test'
Requires-Dist: colorama (>=0.4.3) ; extra == 'test'
Requires-Dist: tqdm (>=4.47.0) ; extra == 'test'
